README.rst
setup.py
Enarksh_Lib.egg-info/PKG-INFO
Enarksh_Lib.egg-info/SOURCES.txt
Enarksh_Lib.egg-info/dependency_links.txt
Enarksh_Lib.egg-info/top_level.txt
enarksh_lib/__init__.py
enarksh_lib/xml_generator/__init__.py
enarksh_lib/xml_generator/consumption/Consumption.py
enarksh_lib/xml_generator/consumption/CountingConsumption.py
enarksh_lib/xml_generator/consumption/ReadWriteLockConsumption.py
enarksh_lib/xml_generator/consumption/__init__.py
enarksh_lib/xml_generator/node/CommandJobNode.py
enarksh_lib/xml_generator/node/CompoundJobNode.py
enarksh_lib/xml_generator/node/ManualTriggerNode.py
enarksh_lib/xml_generator/node/Node.py
enarksh_lib/xml_generator/node/ScheduleNode.py
enarksh_lib/xml_generator/node/TerminatorNode.py
enarksh_lib/xml_generator/node/__init__.py
enarksh_lib/xml_generator/port/InputPort.py
enarksh_lib/xml_generator/port/OutputPort.py
enarksh_lib/xml_generator/port/Port.py
enarksh_lib/xml_generator/port/__init__.py
enarksh_lib/xml_generator/resource/CountingResource.py
enarksh_lib/xml_generator/resource/ReadWriteLockResource.py
enarksh_lib/xml_generator/resource/Resource.py
enarksh_lib/xml_generator/resource/__init__.py
test/xml_generator/ScheduleTest.py
test/xml_generator/__init__.py